{
  "source": "Alpha Vantage",
  "ts": "2026-06-15T20:54:16.184844+00:00",
  "quotes": [
    {
      "symbol": "AAPL",
      "price": "N/A",
      "change_pct": "N/A",
      "volume": "N/A"
    },
    {
      "symbol": "MSFT",
      "price": "399.7600",
      "change_pct": "2.3084%",
      "volume": "32016705"
    },
    {
      "symbol": "GOOGL",
      "price": "N/A",
      "change_pct": "N/A",
      "volume": "N/A"
    },
    {
      "symbol": "AMZN",
      "price": "N/A",
      "change_pct": "N/A",
      "volume": "N/A"
    },
    {
      "symbol": "TSLA",
      "price": "N/A",
      "change_pct": "N/A",
      "volume": "N/A"
    },
    {
      "symbol": "SPY",
      "price": "N/A",
      "change_pct": "N/A",
      "volume": "N/A"
    },
    {
      "symbol": "QQQ",
      "price": "N/A",
      "change_pct": "N/A",
      "volume": "N/A"
    }
  ]
}